README.md
setup.py
distributionsbyme/Binomialdistribution.py
distributionsbyme/Gaussiandistribution.py
distributionsbyme/Generaldistribution.py
distributionsbyme/__init__.py
distributionsbyme.egg-info/PKG-INFO
distributionsbyme.egg-info/SOURCES.txt
distributionsbyme.egg-info/dependency_links.txt
distributionsbyme.egg-info/not-zip-safe
distributionsbyme.egg-info/top_level.txt