Metadata-Version: 1.0
Name: distributionsbyme
Version: 0.1
Summary: Gaussian distributions
Home-page: UNKNOWN
Author: Maria
Author-email: UNKNOWN
License: UNKNOWN
Platform: UNKNOWN
